molmass/__init__.py
molmass/__main__.py
molmass/elements.py
molmass/elements_descriptions.py
molmass/elements_gui.py
molmass/icon.png
molmass/molmass.py
molmass/py.typed
molmass/web.py
molmass-2026.1.8.dist-info/licenses/LICENSE
molmass-2026.1.8.dist-info/METADATA
molmass-2026.1.8.dist-info/WHEEL
molmass-2026.1.8.dist-info/entry_points.txt
molmass-2026.1.8.dist-info/top_level.txt
molmass-2026.1.8.dist-info/RECORD
