Metadata-Version: 2.4
Name: molmass
Version: 2026.1.8
Summary: Molecular mass calculations
Home-page: https://www.cgohlke.com
Author: Christoph Gohlke
Author-email: cgohlke@cgohlke.com
License: BSD-3-Clause
Project-URL: Bug Tracker, https://github.com/cgohlke/molmass/issues
Project-URL: Source Code, https://github.com/cgohlke/molmass
Platform: any
Classifier: Development Status :: 4 - Beta
Classifier: Intended Audience :: Science/Research
Classifier: Intended Audience :: Developers
Classifier: Operating System :: OS Independent
Classifier: Programming Language :: Python :: 3 :: Only
Classifier: Programming Language :: Python :: 3.11
Classifier: Programming Language :: Python :: 3.12
Classifier: Programming Language :: Python :: 3.13
Classifier: Programming Language :: Python :: 3.14
Requires-Python: >=3.11
License-File: LICENSE
Provides-Extra: all
Requires-Dist: Flask; extra == "all"
Requires-Dist: pandas; extra == "all"
Provides-Extra: gui
Requires-Dist: wxPython>=4.0; extra == "gui"
Dynamic: author
Dynamic: author-email
Dynamic: classifier
Dynamic: description
Dynamic: description-content-type
Dynamic: home-page
Dynamic: license
Dynamic: license-file
Dynamic: platform
Dynamic: project-url
Dynamic: provides-extra
Dynamic: requires-python
Dynamic: summary
